{
  "pages": [
    {
      "path": "./Overview.md",
      "displayName": "Overview"
    },
    {
      "path": "./Creating_a_Player.md",
      "displayName": "Creating a Player"
    },
    {
      "path": "./Loading_a_Content.md",
      "displayName": "Loading a Content"
    },
    {
      "path": "./Decryption_Options.md",
      "displayName": "Decryption Options"
    },
    {
      "path": "./Basic_Methods",
      "displayName": "Basic Methods"
    },
    {
      "path": "./Player_States.md",
      "displayName": "Player States"
    },
    {
      "path": "./Player_Events.md",
      "displayName": "Player Events"
    },
    {
      "path": "./Player_Errors.md",
      "displayName": "Player Errors"
    },
    {
      "path": "./Track_Selection",
      "displayName": "Track Selection"
    },
    {
      "path": "./Representation_Selection",
      "displayName": "Representation Selection"
    },
    {
      "path": "./Bitrate_Control",
      "displayName": "Bitrate Control"
    },
    {
      "path": "./Speed_Control",
      "displayName": "Speed Control"
    },
    {
      "path": "./Volume_Control",
      "displayName": "Volume Control"
    },
    {
      "path": "./Buffer_Control",
      "displayName": "Buffer Control"
    },
    {
      "path": "./Buffer_Information",
      "displayName": "Buffer Information"
    },
    {
      "path": "./Content_Information",
      "displayName": "Content Information"
    },
    {
      "path": "./Static_Properties.md",
      "displayName": "RxPlayer Static Properties"
    },
    {
      "path": "./Typescript_Types.md",
      "displayName": "Typescript Types"
    },
    {
      "path": "./Tools",
      "displayName": "Tools"
    },
    {
      "path": "./Miscellaneous",
      "displayName": "Miscellaneous"
    }
  ]
}
